LICENSE
myfans_client/__init__.py
myfans_client/client.py
myfans_client/exceptions.py
myfans_client/models/__init__.py
myfans_client/models/follow.py
myfans_client/models/user.py
myfans_client-0.0.6.dist-info/LICENSE
myfans_client-0.0.6.dist-info/METADATA
myfans_client-0.0.6.dist-info/WHEEL
myfans_client-0.0.6.dist-info/RECORD
